carconnectivity_plugin_webui-0.7.1.dist-info/licenses/LICENSE
carconnectivity_plugins/webui/__init__.py
carconnectivity_plugins/webui/_version.py
carconnectivity_plugins/webui/plugin.py
carconnectivity_plugins/webui/ui/__init__.py
carconnectivity_plugins/webui/ui/cache.py
carconnectivity_plugins/webui/ui/connectors.py
carconnectivity_plugins/webui/ui/garage.py
carconnectivity_plugins/webui/ui/plugin_ui.py
carconnectivity_plugins/webui/ui/plugins.py
carconnectivity_plugins/webui/ui/webui.py
carconnectivity_plugins/webui/ui/static/css/bootstrap-grid.css
carconnectivity_plugins/webui/ui/static/css/bootstrap-grid.css.map
carconnectivity_plugins/webui/ui/static/css/bootstrap-grid.min.css
carconnectivity_plugins/webui/ui/static/css/bootstrap-grid.min.css.map
carconnectivity_plugins/webui/ui/static/css/bootstrap-grid.rtl.css
carconnectivity_plugins/webui/ui/static/css/bootstrap-grid.rtl.css.map
carconnectivity_plugins/webui/ui/static/css/bootstrap-grid.rtl.min.css
carconnectivity_plugins/webui/ui/static/css/bootstrap-grid.rtl.min.css.map
carconnectivity_plugins/webui/ui/static/css/bootstrap-reboot.css
carconnectivity_plugins/webui/ui/static/css/bootstrap-reboot.css.map
carconnectivity_plugins/webui/ui/static/css/bootstrap-reboot.min.css
carconnectivity_plugins/webui/ui/static/css/bootstrap-reboot.min.css.map
carconnectivity_plugins/webui/ui/static/css/bootstrap-reboot.rtl.css
carconnectivity_plugins/webui/ui/static/css/bootstrap-reboot.rtl.css.map
carconnectivity_plugins/webui/ui/static/css/bootstrap-reboot.rtl.min.css
carconnectivity_plugins/webui/ui/static/css/bootstrap-reboot.rtl.min.css.map
carconnectivity_plugins/webui/ui/static/css/bootstrap-utilities.css
carconnectivity_plugins/webui/ui/static/css/bootstrap-utilities.css.map
carconnectivity_plugins/webui/ui/static/css/bootstrap-utilities.min.css
carconnectivity_plugins/webui/ui/static/css/bootstrap-utilities.min.css.map
carconnectivity_plugins/webui/ui/static/css/bootstrap-utilities.rtl.css
carconnectivity_plugins/webui/ui/static/css/bootstrap-utilities.rtl.css.map
carconnectivity_plugin_webui-0.7.1.dist-info/METADATA
carconnectivity_plugin_webui-0.7.1.dist-info/WHEEL
carconnectivity_plugin_webui-0.7.1.dist-info/top_level.txt
carconnectivity_plugin_webui-0.7.1.dist-info/RECORD
