Metadata-Version: 2.4
Name: carconnectivity-plugin-webui
Version: 0.7.1
Summary: CarConnectivity plugin for a web based user interface
Author: Till Steinbach
License-Expression: MIT
Classifier: Development Status :: 3 - Alpha
Classifier: Intended Audience :: End Users/Desktop
Classifier: Intended Audience :: System Administrators
Classifier: Programming Language :: Python :: 3.9
Classifier: Programming Language :: Python :: 3.10
Classifier: Programming Language :: Python :: 3.11
Classifier: Programming Language :: Python :: 3.12
Classifier: Programming Language :: Python :: 3.13
Classifier: Programming Language :: Python :: 3.14
Classifier: Topic :: Utilities
Classifier: Topic :: System :: Monitoring
Classifier: Topic :: Home Automation
Requires-Python: >=3.9
License-File: LICENSE
Requires-Dist: carconnectivity[images]>=0.11.6
Requires-Dist: Werkzeug~=3.1.3
Requires-Dist: Flask~=3.1.2
Requires-Dist: flask-login~=0.6.3
Requires-Dist: flask-caching~=2.3.1
Requires-Dist: WTForms~=3.2.1
Requires-Dist: flask_wtf~=1.2.2
Requires-Dist: pypng~=0.20220715.0
Requires-Dist: Bootstrap-Flask~=2.5.0
Dynamic: license-file
